CHANGES.txt
LICENSE.txt
MANIFEST.in
README.rst
buildout.cfg
setup.py
js/__init__.py
js.qrious.egg-info/PKG-INFO
js.qrious.egg-info/SOURCES.txt
js.qrious.egg-info/dependency_links.txt
js.qrious.egg-info/entry_points.txt
js.qrious.egg-info/namespace_packages.txt
js.qrious.egg-info/not-zip-safe
js.qrious.egg-info/requires.txt
js.qrious.egg-info/top_level.txt
js/qrious/__init__.py
js/qrious/test_qrious.txt
js/qrious/resources/qrious.js
js/qrious/resources/qrious.min.js