Metadata-Version: 1.1
Name: js.qrious
Version: 4.0.2
Summary: Fanstatic packaging of Qrious
Home-page: https://github.com/minddistrict/js.qrious
Author: UNKNOWN
Author-email: UNKNOWN
License: MIT
Platform: UNKNOWN
Classifier: Programming Language :: Python :: 2.6
Classifier: Programming Language :: Python :: 2.7
Classifier: Programming Language :: Python :: 3.2
Classifier: Programming Language :: Python :: Implementation :: PyPy
